apist/__init__.py
apist/apist.py
apist/emails.py
apist/excel_orm.py
apist/logs.py
apist/setting.py
apist-2.10.dist-info/LICENSE
apist-2.10.dist-info/METADATA
apist-2.10.dist-info/WHEEL
apist-2.10.dist-info/top_level.txt
apist-2.10.dist-info/RECORD
