Metadata-Version: 2.1
Name: apist
Version: 2.10
Summary: apist, The best framework for api automation testing
Home-page: https://gitee.com/teark/apist.git
Author: Teark
Author-email: 913355434@qq.com
License: UNKNOWN
Platform: UNKNOWN
Classifier: Programming Language :: Python :: 3
Classifier: License :: OSI Approved :: MIT License
Classifier: Operating System :: OS Independent
License-File: LICENSE
Requires-Dist: requests
Requires-Dist: xlutils
Requires-Dist: jsonpath
Requires-Dist: bottle
